{
"name":"Atlas Intelligence Engine",
"version":"1.0",

"hierarchy":{

"director":"atlas",

"departments":[

{
"name":"Engineering",
"lead":"builder",
"agents":[
"frontend",
"backend",
"mobile",
"cloud"
]
},

{
"name":"Defense",
"lead":"guardian",
"agents":[
"security",
"recovery",
"validator"
]
},

{
"name":"Knowledge",
"lead":"researcher",
"agents":[
"rag",
"memory",
"document-analyzer"
]
},

{
"name":"Optimization",
"lead":"optimizer",
"agents":[
"seo",
"performance",
"ux"
]
}

]

},

"decisionFlow":[
"understand",
"retrieve-context",
"plan",
"execute",
"verify",
"report"
]

}
